dbpipe/__init__.py
dbpipe/core/__init__.py
dbpipe/core/pipes.py
dbpipe/io/__init__.py
dbpipe/io/jsonreader.py
dbpipe/lineage/__init__.py
dbpipe/lineage/mermaid.py
dbpipe-0.2.0.dist-info/LICENSE
dbpipe-0.2.0.dist-info/METADATA
dbpipe-0.2.0.dist-info/WHEEL
dbpipe-0.2.0.dist-info/top_level.txt
dbpipe-0.2.0.dist-info/RECORD
