Metadata-Version: 2.1
Name: dbpipe
Version: 0.2.0
Summary: Lightweight DataPipeline Documentation
Home-page: https://github.com/jrasband-dev/dbpipe
Author: Jayden Rasband
Author-email: jayden.rasband@gmail.com
License: MIT
License-File: LICENSE
